eaw2web/__init__.py
eaw2web/__main__.py
eaw2web/cli/__init__.py
eaw2web/cli/progressreporters.py
eaw2web/cli/wrappers.py
eaw2web/config.py
eaw2web/export/__init__.py
eaw2web/export/icons.py
eaw2web/export/json.py
eaw2web/export/templates/campaign.xml.j2
eaw2web/export/xml.py
eaw2web/filters/__init__.py
eaw2web/filters/playablefaction.py
eaw2web/gameobjecttypes/__init__.py
eaw2web/gameobjecttypes/atomics.py
eaw2web/gameobjecttypes/campaign.py
eaw2web/gameobjecttypes/faction.py
eaw2web/gameobjecttypes/generic.py
eaw2web/gameobjecttypes/planet.py
eaw2web/gameobjecttypes/unit.py
eaw2web/gameobjecttypes/variants.py
eaw2web/icon.py
eaw2web/load.py
eaw2web/modstack.py
eaw2web/pipeline.py
eaw2web/text.py
eaw2web/transformers/__init__.py
eaw2web/transformers/campaignsets.py
eaw2web/typing.py
eaw2web/writers.py
eaw2web/xml/__init__.py
eaw2web/xml/base.py
eaw2web/xml/campaign.py
eaw2web/xml/collectors.py
eaw2web/xml/faction.py
eaw2web/xml/generic.py
eaw2web/xml/icon.py
eaw2web/xml/planet.py
eaw2web/xml/tags.py
eaw2web/xml/text.py
eaw2web/xml/textentries.py
eaw2web/xml/traderoutes.py
eaw2web/xml/units.py
eaw2web-0.4.0.dist-info/entry_points.txt
eaw2web-0.4.0.dist-info/WHEEL
eaw2web-0.4.0.dist-info/METADATA
eaw2web-0.4.0.dist-info/RECORD
